LICENSE
MANIFEST.in
README.md
setup.cfg
setup.py
loompy/__init__.py
loompy/_version.py
loompy/attribute_manager.py
loompy/bus_file.py
loompy/cell_calling.py
loompy/commands.py
loompy/global_attribute_manager.py
loompy/graph_manager.py
loompy/layer_manager.py
loompy/loom_layer.py
loompy/loom_validator.py
loompy/loom_view.py
loompy/loompy.py
loompy/metadata_loaders.py
loompy/normalize.py
loompy/to_html.py
loompy/utils.py
loompy/view_manager.py
loompy.egg-info/PKG-INFO
loompy.egg-info/SOURCES.txt
loompy.egg-info/dependency_links.txt
loompy.egg-info/entry_points.txt
loompy.egg-info/requires.txt
loompy.egg-info/top_level.txt
tests/test_attribute_manager.py
tests/test_connection.py
tests/test_file_attribute_manager.py
tests/test_main.py
tests/test_validator.py